TermCmds/__init__.py
TermCmds/compile.py
TermCmds-0.0.3.dist-info/METADATA
TermCmds-0.0.3.dist-info/WHEEL
TermCmds-0.0.3.dist-info/entry_points.txt
TermCmds-0.0.3.dist-info/top_level.txt
TermCmds-0.0.3.dist-info/RECORD
