Metadata-Version: 2.1
Name: TermCmds
Version: 0.0.3
Summary: Make custom terminal commands in python.
Home-page: UNKNOWN
Author: Natejoestev
License: UNKNOWN
Keywords: terminal,TermCmds,commands,cmds,term,python
Platform: UNKNOWN
Classifier: Operating System :: Microsoft :: Windows
Classifier: Programming Language :: Python :: 3
Classifier: Intended Audience :: Developers
